opentargets_checkomatic/__init__.py
opentargets_checkomatic/cli.py
opentargets_checkomatic/evaluators.py
opentargets_checkomatic/helpers.py
opentargets_checkomatic/data/drugs.txt
opentargets_checkomatic/data/efos.txt
opentargets_checkomatic/data/genes.txt
opentargets_checkomatic/data/platform.yml
opentargets_checkomatic-0.2.5.dist-info/LICENSE
opentargets_checkomatic-0.2.5.dist-info/METADATA
opentargets_checkomatic-0.2.5.dist-info/WHEEL
opentargets_checkomatic-0.2.5.dist-info/entry_points.txt
opentargets_checkomatic-0.2.5.dist-info/top_level.txt
opentargets_checkomatic-0.2.5.dist-info/RECORD
