Metadata-Version: 2.1
Name: opentargets-checkomatic
Version: 0.2.5
Summary: This package handles the Open Targets data checking.
Home-page: http://github.com/opentargets/checkomatic
Author: OpenTargets Core Team <core@opentargets.org>
Author-email: OpenTargets Core Team <core@opentargets.org>
Maintainer: Miguel Carmona
Maintainer-email: carmona@ebi.ac.uk
License: Apache License, Version 2.0
Keywords: opentargets,bioinformatics,python2
Platform: any
Requires-Dist: jsonpath-rw
Requires-Dist: more-itertools
Requires-Dist: bpython
Requires-Dist: pyfunctional
Requires-Dist: pyyaml
Requires-Dist: addict
Requires-Dist: docopt
Requires-Dist: opentargets
